[
  {
    "id": "main",
    "components": [
      "section"
    ]
  },
  {
    "id": "section",
    "components": [
      "text",
      "image",
      "button",
      "title",
      "hero",
      "cards",
      "carousel",
      "carouselzo",
      "sectionheader",
      "columns",
      "fragment"
    ]
  },
  {
    "id": "cards",
    "components": [
      "card"
    ]
  },
  {
    "id": "columns",
    "components": [
      "column"
    ]
  },
  {
    "id": "column",
    "components": [
      "text",
      "image",
      "button",
      "title"
    ]
  },
  {
    "id": "carousel",
    "components": [
      "carousel-item"
    ]
  },
  {
    "id": "carouselzo",
    "include": true,
    "components": [
      "carousel-item"
    ]
  },
   {
    "id": "sectionheader",
    "include": true,
    "components": [
      "text"
    ]
  }
  
]
